<?xml version="1.0" encoding="UTF-8"?>
<!DOCTYPE mapper PUBLIC "-//mybatis.org//DTD Mapper 3.0//EN" "http://mybatis.org/dtd/mybatis-3-mapper.dtd">
<mapper namespace="com.joiest.jpf.dao.repository.mapper.custom.PayShopOrderCustomMapper">
  <resultMap id="BaseResultMap" type="com.joiest.jpf.common.custom.PayShopOrderCustom">
    <!--
      @mbggenerated
      This element is automatically generated by MyBatis Generator,Do not modify ! Generated on Fri Aug 03 13:59:18 CST 2018.
    -->
    <id column="id" jdbcType="BIGINT" property="id" />
    <result column="order_no" jdbcType="VARCHAR" property="orderNo" />
    <result column="charge_type" jdbcType="TINYINT" property="chargeType" />
    <result column="stock_card_id" jdbcType="BIGINT" property="stockCardId" />
    <result column="order_type" jdbcType="TINYINT" property="orderType" />
    <result column="foreign_order_no" jdbcType="VARCHAR" property="foreignOrderNo" />
    <result column="requested_content" jdbcType="VARCHAR" property="requestedContent" />
    <result column="foreign_request_content" jdbcType="VARCHAR" property="foreignRequestContent" />
    <result column="foreign_response_content" jdbcType="VARCHAR" property="foreignResponseContent" />
    <result column="customer_id" jdbcType="BIGINT" property="customerId" />
    <result column="customer_name" jdbcType="VARCHAR" property="customerName" />
    <result column="product_id" jdbcType="BIGINT" property="productId" />
    <result column="product_name" jdbcType="VARCHAR" property="productName" />
    <result column="product_money" jdbcType="DECIMAL" property="productMoney" />
    <result column="product_dou" jdbcType="DECIMAL" property="productDou" />
    <result column="product_info_id" jdbcType="INTEGER" property="productInfoId" />
    <result column="wn_product_id" jdbcType="BIGINT" property="wnProductId" />
    <result column="amount" jdbcType="INTEGER" property="amount" />
    <result column="total_money" jdbcType="DECIMAL" property="totalMoney" />
    <result column="total_dou" jdbcType="DECIMAL" property="totalDou" />
    <result column="pay_way" jdbcType="TINYINT" property="payWay" />
    <result column="charge_no" jdbcType="VARCHAR" property="chargeNo" />
    <result column="coupon_detail" jdbcType="VARCHAR" property="couponDetail" />
    <result column="status" jdbcType="TINYINT" property="status" />
    <result column="recharge_status" jdbcType="VARCHAR" property="rechargeStatus" />
    <result column="recharge_time" jdbcType="TIMESTAMP" property="rechargeTime" />
    <result column="coupon_active_id" jdbcType="VARCHAR" property="couponActiveId" />
    <result column="receive_type" jdbcType="TINYINT" property="receiveType" />
    <result column="receive_value" jdbcType="VARCHAR" property="receiveValue" />
    <result column="oss_url" jdbcType="VARCHAR" property="ossUrl" />
    <result column="source" jdbcType="TINYINT" property="source" />
    <result column="interface_type" jdbcType="TINYINT" property="interfaceType" />
    <result column="bargain_order_id" jdbcType="BIGINT" property="bargainOrderId" />
    <result column="bargain_order_no" jdbcType="VARCHAR" property="bargainOrderNo" />
    <result column="addtime" jdbcType="TIMESTAMP" property="addtime" />
    <result column="paytime" jdbcType="TIMESTAMP" property="paytime" />
    <result column="updatetime" jdbcType="TIMESTAMP" property="updatetime" />
<!--商品基础信息-->
    <result column="type_name" property="typeName" jdbcType="VARCHAR" />
    <result column="supplier_name" property="supplierName" jdbcType="VARCHAR" />
    <result column="brand_name" property="brandName" jdbcType="VARCHAR" />
    <result column="contact_name" property="contactName" jdbcType="VARCHAR" />
    <result column="contact_phone" property="contactPhone" jdbcType="VARCHAR" />
    <result column="contact_email" property="contactEmail" jdbcType="VARCHAR" />
<!--客户信息-->
    <result column="phone" property="phone" jdbcType="VARCHAR" />
    <!--商品信息-->
    <result column="image" jdbcType="VARCHAR" property="image" />
    <result column="bid" jdbcType="DECIMAL" property="bid" />
    <result column="stored" jdbcType="INTEGER" property="stored" />
    <result column="money" jdbcType="DECIMAL" property="money" />
    <result column="recharge_money" jdbcType="INTEGER" property="rechargeMoney" />
  </resultMap>

  <sql id="Example_Where_Clause_Custom">
    <!--
      @mbggenerated
      This element is automatically generated by MyBatis Generator,Do not modify ! Generated on Fri Aug 03 13:59:18 CST 2018.
    -->
    <where>
      <foreach collection="oredCriteria" item="criteria" separator="or">
        <if test="criteria.valid">
          <trim prefix="(" prefixOverrides="and" suffix=")">
            <foreach collection="criteria.criteria" item="criterion">
              <choose>
                <when test="criterion.noValue">
                  and a.${criterion.condition}
                </when>
                <when test="criterion.singleValue">
                  and a.${criterion.condition} #{criterion.value}
                </when>
                <when test="criterion.betweenValue">
                  and a.${criterion.condition} #{criterion.value} and #{criterion.secondValue}
                </when>
                <when test="criterion.listValue">
                  and a.${criterion.condition}
                  <foreach close=")" collection="criterion.value" item="listItem" open="(" separator=",">
                    #{listItem}
                  </foreach>
                </when>
              </choose>
            </foreach>
          </trim>
        </if>
      </foreach>
    </where>
  </sql>

  <sql id="Example_Where_Clause_Custom_List">
    <!--
      @mbggenerated
      This element is automatically generated by MyBatis Generator,Do not modify ! Generated on Fri Aug 03 13:59:18 CST 2018.
    -->
    <where>
      <foreach collection="oredCriteria" item="criteria" separator="and">
        <if test="criteria.valid">
          <trim prefix="(" prefixOverrides="or" suffix=")">
            <foreach collection="criteria.criteria" item="criterion">
              <choose>
                <when test="criterion.noValue">
                  or a.${criterion.condition}
                </when>
                <when test="criterion.singleValue">
                  or a.${criterion.condition} #{criterion.value}
                </when>
                <when test="criterion.betweenValue">
                  or a.${criterion.condition} #{criterion.value} and #{criterion.secondValue}
                </when>
                <when test="criterion.listValue">
                  or a.${criterion.condition}
                  <foreach close=")" collection="criterion.value" item="listItem" open="(" separator=",">
                    #{listItem}
                  </foreach>
                </when>
              </choose>
            </foreach>
          </trim>
        </if>
      </foreach>
    </where>
  </sql>

  <sql id="Example_Where_Clause">
    <!--
      @mbggenerated
      This element is automatically generated by MyBatis Generator,Do not modify ! Generated on Fri Aug 03 13:59:18 CST 2018.
    -->
    <where>
      <foreach collection="oredCriteria" item="criteria" separator="or">
        <if test="criteria.valid">
          <trim prefix="(" prefixOverrides="and" suffix=")">
            <foreach collection="criteria.criteria" item="criterion">
              <choose>
                <when test="criterion.noValue">
                  and ${criterion.condition}
                </when>
                <when test="criterion.singleValue">
                  and ${criterion.condition} #{criterion.value}
                </when>
                <when test="criterion.betweenValue">
                  and ${criterion.condition} #{criterion.value} and #{criterion.secondValue}
                </when>
                <when test="criterion.listValue">
                  and ${criterion.condition}
                  <foreach close=")" collection="criterion.value" item="listItem" open="(" separator=",">
                    #{listItem}
                  </foreach>
                </when>
              </choose>
            </foreach>
          </trim>
        </if>
      </foreach>
    </where>
  </sql>
  <sql id="Update_By_Example_Where_Clause">
    <!--
      @mbggenerated
      This element is automatically generated by MyBatis Generator,Do not modify ! Generated on Fri Aug 03 13:59:18 CST 2018.
    -->
    <where>
      <foreach collection="example.oredCriteria" item="criteria" separator="or">
        <if test="criteria.valid">
          <trim prefix="(" prefixOverrides="and" suffix=")">
            <foreach collection="criteria.criteria" item="criterion">
              <choose>
                <when test="criterion.noValue">
                  and ${criterion.condition}
                </when>
                <when test="criterion.singleValue">
                  and ${criterion.condition} #{criterion.value}
                </when>
                <when test="criterion.betweenValue">
                  and ${criterion.condition} #{criterion.value} and #{criterion.secondValue}
                </when>
                <when test="criterion.listValue">
                  and ${criterion.condition}
                  <foreach close=")" collection="criterion.value" item="listItem" open="(" separator=",">
                    #{listItem}
                  </foreach>
                </when>
              </choose>
            </foreach>
          </trim>
        </if>
      </foreach>
    </where>
  </sql>
  <sql id="Base_Column_List">
    <!--
      @mbggenerated
      This element is automatically generated by MyBatis Generator,Do not modify ! Generated on Fri Aug 03 13:59:18 CST 2018.
    -->
    id, order_no, customer_id, customer_name, product_id, product_name, product_money, 
    product_dou, product_info_id, amount, total_money, total_dou, pay_way, charge_no, 
    coupon_detail, status, coupon_active_id, addtime, paytime, updatetime
  </sql>
  <select id="selectByExample" parameterType="com.joiest.jpf.common.po.PayShopOrderExample" resultMap="BaseResultMap">
    <!--
      @mbggenerated
      This element is automatically generated by MyBatis Generator,Do not modify ! Generated on Fri Aug 03 13:59:18 CST 2018.
    -->
    select
    <if test="distinct">
      distinct
    </if>
    <include refid="Base_Column_List" />
    from pay_shop_order
    <if test="_parameter != null">
      <include refid="Example_Where_Clause_Custom" />
    </if>
    <if test="orderByClause != null">
      order by ${orderByClause}
    </if>
    <if test="pageNo &gt; 0 and pageSize &gt; 0">
      limit ${(pageNo-1) * pageSize}, ${pageSize}
    </if>
  </select>

  <!--自定义连表查询数据-->
  <select id="selectByExampleJoin" parameterType="com.joiest.jpf.common.po.PayShopOrderExample" resultMap="BaseResultMap">
    <!--
      @mbggenerated
      This element is automatically generated by MyBatis Generator,Do not modify ! Generated on Fri Aug 03 13:59:18 CST 2018.
    -->
    select a.*,b.type_name,b.supplier_name,b.brand_name,b.contact_name,b.contact_phone,b.contact_email from pay_shop_order a
    LEFT JOIN  pay_shop_product_info b ON  a.product_info_id=b.id
    <if test="_parameter != null">
      <include refid="Example_Where_Clause_Custom" />
    </if>
    <if test="orderByClause != null">
      order by ${orderByClause}
    </if>
    <if test="pageNo &gt; 0 and pageSize &gt; 0">
      limit ${(pageNo-1) * pageSize}, ${pageSize}
    </if>
  </select>

  <!--自定义连表查询 单条业务  -->
  <select id="selectOrderAll" parameterType="com.joiest.jpf.common.po.PayShopOrderExample" resultMap="BaseResultMap">

  select a.*,b.type_name,b.supplier_name,b.brand_name,b.contact_name,b.contact_phone,b.contact_email,c.phone,d.image,d.bid,d.stored
    from pay_shop_order a
    LEFT JOIN  pay_shop_product_info b ON  a.product_info_id=b.id
    LEFT  JOIN   pay_shop_customer c ON a.customer_id=c.id
    LEFT JOIN pay_shop_product d ON  a.product_id=d.id

    <if test="_parameter != null">
      <include refid="Example_Where_Clause_Custom" />
    </if>

  </select>

  <!--自定义连表查询 单条业务  -->
  <select id="selectOrderInterfaceAll" parameterType="java.lang.String" resultMap="BaseResultMap">

    select a.*,b.type_name,b.supplier_name,b.brand_name,b.contact_name,b.contact_phone,b.contact_email,c.phone,d.image,d.bid,d.stored
    ,d.money,d.recharge_money
    from pay_shop_order a
    LEFT JOIN  pay_shop_product_info b ON  a.product_info_id=b.id
    LEFT  JOIN   pay_shop_customer c ON a.customer_id=c.id
    LEFT JOIN pay_shop_product d ON  a.product_id=d.id
    <if test="_parameter != null">
      <include refid="Example_Where_Clause_Custom" />
    </if>

  </select>

  <!--前台接口订单列表 自定义连表查询数据-->
  <select id="selectByExampleInterfaceJoin" parameterType="com.joiest.jpf.common.custom.PayShopOrderCustomExample" resultMap="BaseResultMap">
    <!--
      This element is automatically generated by MyBatis Generator,Do not modify ! Generated on Fri Aug 03 13:59:18 CST 2018.
    -->
    select a.id,a.order_no,a.charge_type,a.stock_card_id,a.order_type,a.foreign_order_no,a.requested_content,a.foreign_request_content,a.foreign_response_content,a.customer_id,a.customer_name,a.product_id,a.product_name,
    a.product_money,a.product_dou,a.product_info_id,a.amount,a.total_money,a.total_dou,a.total_dou as recharge_money,a.pay_way,a.charge_no,a.coupon_detail,a.status,a.recharge_status,a.recharge_time,a.coupon_active_id,a.receive_type,
    a.receive_value,a.oss_url,a.addtime,a.paytime,a.updatetime,
    b.type_name,b.supplier_name,b.brand_name,b.contact_name,b.contact_phone,b.contact_email,c.phone,
    d.image,d.bid,d.stored,d.money
    from pay_shop_order a
    LEFT JOIN pay_shop_product_info b ON  a.product_info_id=b.id
    LEFT JOIN pay_shop_customer c ON a.customer_id=c.id
    LEFT JOIN pay_shop_product d ON  a.product_id=d.id
    <if test="_parameter != null">
      <include refid="Example_Where_Clause_Custom_List" />
    </if>
    <if test="orderByClause != null">
      order by ${orderByClause}
    </if>
    <if test="pageNo &gt; 0 and pageSize &gt; 0">
      limit ${(pageNo-1) * pageSize}, ${pageSize}
    </if>
  </select>

  <select id="selectByPrimaryKey" parameterType="java.lang.String" resultMap="BaseResultMap">
    <!--
      @mbggenerated
      This element is automatically generated by MyBatis Generator,Do not modify ! Generated on Fri Aug 03 13:59:18 CST 2018.
    -->
    select 
    <include refid="Base_Column_List" />
    from pay_shop_order
    where id = #{id,jdbcType=BIGINT}
  </select>
  <delete id="deleteByPrimaryKey" parameterType="java.lang.String">
    <!--
      @mbggenerated
      This element is automatically generated by MyBatis Generator,Do not modify ! Generated on Fri Aug 03 13:59:18 CST 2018.
    -->
    delete from pay_shop_order
    where id = #{id,jdbcType=BIGINT}
  </delete>
  <delete id="deleteByExample" parameterType="com.joiest.jpf.common.po.PayShopOrderExample">
    <!--
      @mbggenerated
      This element is automatically generated by MyBatis Generator,Do not modify ! Generated on Fri Aug 03 13:59:18 CST 2018.
    -->
    delete from pay_shop_order
    <if test="_parameter != null">
      <include refid="Example_Where_Clause" />
    </if>
  </delete>
  <insert id="insert" parameterType="com.joiest.jpf.common.po.PayShopOrder">
    <!--
      @mbggenerated
      This element is automatically generated by MyBatis Generator,Do not modify ! Generated on Fri Aug 03 13:59:18 CST 2018.
    -->
    insert into pay_shop_order (id, order_no, customer_id, 
      customer_name, product_id, product_name, 
      product_money, product_dou, product_info_id, 
      amount, total_money, total_dou, 
      pay_way, charge_no, coupon_detail, 
      status, coupon_active_id, addtime, 
      paytime, updatetime)
    values (#{id,jdbcType=BIGINT}, #{orderNo,jdbcType=VARCHAR}, #{customerId,jdbcType=BIGINT}, 
      #{customerName,jdbcType=VARCHAR}, #{productId,jdbcType=BIGINT}, #{productName,jdbcType=VARCHAR}, 
      #{productMoney,jdbcType=DECIMAL}, #{productDou,jdbcType=INTEGER}, #{productInfoId,jdbcType=INTEGER}, 
      #{amount,jdbcType=INTEGER}, #{totalMoney,jdbcType=DECIMAL}, #{totalDou,jdbcType=INTEGER}, 
      #{payWay,jdbcType=TINYINT}, #{chargeNo,jdbcType=VARCHAR}, #{couponDetail,jdbcType=VARCHAR}, 
      #{status,jdbcType=TINYINT}, #{couponActiveId,jdbcType=BIGINT}, #{addtime,jdbcType=TIMESTAMP}, 
      #{paytime,jdbcType=TIMESTAMP}, #{updatetime,jdbcType=TIMESTAMP})
  </insert>
  <insert id="insertSelective" parameterType="com.joiest.jpf.common.po.PayShopOrder" keyProperty="id" useGeneratedKeys="true">
    <!--
      @mbggenerated
      This element is automatically generated by MyBatis Generator,Do not modify ! Generated on Thu Sep 27 10:21:28 CST 2018.
    -->
    insert into pay_shop_order
    <trim prefix="(" suffix=")" suffixOverrides=",">
      <if test="id != null">
        id,
      </if>
      <if test="orderNo != null">
        order_no,
      </if>
      <if test="chargeType != null">
        charge_type,
      </if>
      <if test="stockCardId != null">
        stock_card_id,
      </if>
      <if test="orderType != null">
        order_type,
      </if>
      <if test="foreignOrderNo != null">
        foreign_order_no,
      </if>
      <if test="requestedContent != null">
        requested_content,
      </if>
      <if test="foreignRequestContent != null">
        foreign_request_content,
      </if>
      <if test="foreignResponseContent != null">
        foreign_response_content,
      </if>
      <if test="customerId != null">
        customer_id,
      </if>
      <if test="customerName != null">
        customer_name,
      </if>
      <if test="productId != null">
        product_id,
      </if>
      <if test="productName != null">
        product_name,
      </if>
      <if test="productMoney != null">
        product_money,
      </if>
      <if test="productDou != null">
        product_dou,
      </if>
      <if test="productInfoId != null">
        product_info_id,
      </if>
      <if test="wnProductId != null">
        wn_product_id,
      </if>
      <if test="amount != null">
        amount,
      </if>
      <if test="totalMoney != null">
        total_money,
      </if>
      <if test="totalDou != null">
        total_dou,
      </if>
      <if test="payWay != null">
        pay_way,
      </if>
      <if test="chargeNo != null">
        charge_no,
      </if>
      <if test="couponDetail != null">
        coupon_detail,
      </if>
      <if test="status != null">
        status,
      </if>
      <if test="rechargeStatus != null">
        recharge_status,
      </if>
      <if test="rechargeTime != null">
        recharge_time,
      </if>
      <if test="couponActiveId != null">
        coupon_active_id,
      </if>
      <if test="receiveType != null">
        receive_type,
      </if>
      <if test="receiveValue != null">
        receive_value,
      </if>
      <if test="ossUrl != null">
        oss_url,
      </if>
      <if test="source != null">
        source,
      </if>
      <if test="interfaceType != null">
        interface_type,
      </if>
      <if test="bargainOrderId != null">
        bargain_order_id,
      </if>
      <if test="bargainOrderNo != null">
        bargain_order_no,
      </if>
      <if test="addtime != null">
        addtime,
      </if>
      <if test="paytime != null">
        paytime,
      </if>
      <if test="updatetime != null">
        updatetime,
      </if>
    </trim>
    <trim prefix="values (" suffix=")" suffixOverrides=",">
      <if test="id != null">
        #{id,jdbcType=BIGINT},
      </if>
      <if test="orderNo != null">
        #{orderNo,jdbcType=VARCHAR},
      </if>
      <if test="chargeType != null">
        #{chargeType,jdbcType=TINYINT},
      </if>
      <if test="stockCardId != null">
        #{stockCardId,jdbcType=BIGINT},
      </if>
      <if test="orderType != null">
        #{orderType,jdbcType=TINYINT},
      </if>
      <if test="foreignOrderNo != null">
        #{foreignOrderNo,jdbcType=VARCHAR},
      </if>
      <if test="requestedContent != null">
        #{requestedContent,jdbcType=VARCHAR},
      </if>
      <if test="foreignRequestContent != null">
        #{foreignRequestContent,jdbcType=VARCHAR},
      </if>
      <if test="foreignResponseContent != null">
        #{foreignResponseContent,jdbcType=VARCHAR},
      </if>
      <if test="customerId != null">
        #{customerId,jdbcType=BIGINT},
      </if>
      <if test="customerName != null">
        #{customerName,jdbcType=VARCHAR},
      </if>
      <if test="productId != null">
        #{productId,jdbcType=BIGINT},
      </if>
      <if test="productName != null">
        #{productName,jdbcType=VARCHAR},
      </if>
      <if test="productMoney != null">
        #{productMoney,jdbcType=DECIMAL},
      </if>
      <if test="productDou != null">
        #{productDou,jdbcType=INTEGER},
      </if>
      <if test="productInfoId != null">
        #{productInfoId,jdbcType=INTEGER},
      </if>
      <if test="wnProductId != null">
        #{wnProductId,jdbcType=BIGINT},
      </if>
      <if test="amount != null">
        #{amount,jdbcType=INTEGER},
      </if>
      <if test="totalMoney != null">
        #{totalMoney,jdbcType=DECIMAL},
      </if>
      <if test="totalDou != null">
        #{totalDou,jdbcType=INTEGER},
      </if>
      <if test="payWay != null">
        #{payWay,jdbcType=TINYINT},
      </if>
      <if test="chargeNo != null">
        #{chargeNo,jdbcType=VARCHAR},
      </if>
      <if test="couponDetail != null">
        #{couponDetail,jdbcType=VARCHAR},
      </if>
      <if test="status != null">
        #{status,jdbcType=TINYINT},
      </if>
      <if test="rechargeStatus != null">
        #{rechargeStatus,jdbcType=VARCHAR},
      </if>
      <if test="rechargeTime != null">
        #{rechargeTime,jdbcType=TIMESTAMP},
      </if>
      <if test="couponActiveId != null">
        #{couponActiveId,jdbcType=VARCHAR},
      </if>
      <if test="receiveType != null">
        #{receiveType,jdbcType=TINYINT},
      </if>
      <if test="receiveValue != null">
        #{receiveValue,jdbcType=VARCHAR},
      </if>
      <if test="ossUrl != null">
        #{ossUrl,jdbcType=VARCHAR},
      </if>
      <if test="source != null">
        #{source,jdbcType=TINYINT},
      </if>
      <if test="interfaceType != null">
        #{interfaceType,jdbcType=TINYINT},
      </if>
      <if test="bargainOrderId != null">
        #{bargainOrderId,jdbcType=BIGINT},
      </if>
      <if test="bargainOrderNo != null">
        #{bargainOrderNo,jdbcType=VARCHAR},
      </if>
      <if test="addtime != null">
        #{addtime,jdbcType=TIMESTAMP},
      </if>
      <if test="paytime != null">
        #{paytime,jdbcType=TIMESTAMP},
      </if>
      <if test="updatetime != null">
        #{updatetime,jdbcType=TIMESTAMP},
      </if>
    </trim>
  </insert>
  <select id="countByExample" parameterType="com.joiest.jpf.common.po.PayShopOrderExample" resultType="java.lang.Integer">
    <!--
      @mbggenerated
      This element is automatically generated by MyBatis Generator,Do not modify ! Generated on Fri Aug 03 13:59:18 CST 2018.
    -->
    select count(*) from pay_shop_order
    <if test="_parameter != null">
      <include refid="Example_Where_Clause" />
    </if>
  </select>

  <select id="countByExampleList" parameterType="com.joiest.jpf.common.po.PayShopOrderExample" resultType="java.lang.Integer">

    select count(*) from pay_shop_order a
    LEFT JOIN  pay_shop_product_info b ON  a.product_info_id=b.id
    LEFT  JOIN   pay_shop_customer c ON a.customer_id=c.id
    LEFT JOIN pay_shop_product d ON  a.product_id=d.id

    <if test="_parameter != null">
      <include refid="Example_Where_Clause_Custom" />
    </if>
  </select>
  <update id="updateByExampleSelective" parameterType="map">
    <!--
      @mbggenerated
      This element is automatically generated by MyBatis Generator,Do not modify ! Generated on Fri Aug 03 13:59:18 CST 2018.
    -->
    update pay_shop_order
    <set>
      <if test="record.id != null">
        id = #{record.id,jdbcType=BIGINT},
      </if>
      <if test="record.orderNo != null">
        order_no = #{record.orderNo,jdbcType=VARCHAR},
      </if>
      <if test="record.customerId != null">
        customer_id = #{record.customerId,jdbcType=BIGINT},
      </if>
      <if test="record.customerName != null">
        customer_name = #{record.customerName,jdbcType=VARCHAR},
      </if>
      <if test="record.productId != null">
        product_id = #{record.productId,jdbcType=BIGINT},
      </if>
      <if test="record.productName != null">
        product_name = #{record.productName,jdbcType=VARCHAR},
      </if>
      <if test="record.productMoney != null">
        product_money = #{record.productMoney,jdbcType=DECIMAL},
      </if>
      <if test="record.productDou != null">
        product_dou = #{record.productDou,jdbcType=INTEGER},
      </if>
      <if test="record.productInfoId != null">
        product_info_id = #{record.productInfoId,jdbcType=INTEGER},
      </if>
      <if test="record.amount != null">
        amount = #{record.amount,jdbcType=INTEGER},
      </if>
      <if test="record.totalMoney != null">
        total_money = #{record.totalMoney,jdbcType=DECIMAL},
      </if>
      <if test="record.totalDou != null">
        total_dou = #{record.totalDou,jdbcType=INTEGER},
      </if>
      <if test="record.payWay != null">
        pay_way = #{record.payWay,jdbcType=TINYINT},
      </if>
      <if test="record.chargeNo != null">
        charge_no = #{record.chargeNo,jdbcType=VARCHAR},
      </if>
      <if test="record.couponDetail != null">
        coupon_detail = #{record.couponDetail,jdbcType=VARCHAR},
      </if>
      <if test="record.status != null">
        status = #{record.status,jdbcType=TINYINT},
      </if>
      <if test="record.couponActiveId != null">
        coupon_active_id = #{record.couponActiveId,jdbcType=BIGINT},
      </if>
      <if test="record.addtime != null">
        addtime = #{record.addtime,jdbcType=TIMESTAMP},
      </if>
      <if test="record.paytime != null">
        paytime = #{record.paytime,jdbcType=TIMESTAMP},
      </if>
      <if test="record.updatetime != null">
        updatetime = #{record.updatetime,jdbcType=TIMESTAMP},
      </if>
    </set>
    <if test="_parameter != null">
      <include refid="Update_By_Example_Where_Clause" />
    </if>
  </update>
  <update id="updateByExample" parameterType="map">
    <!--
      @mbggenerated
      This element is automatically generated by MyBatis Generator,Do not modify ! Generated on Fri Aug 03 13:59:18 CST 2018.
    -->
    update pay_shop_order
    set id = #{record.id,jdbcType=BIGINT},
      order_no = #{record.orderNo,jdbcType=VARCHAR},
      customer_id = #{record.customerId,jdbcType=BIGINT},
      customer_name = #{record.customerName,jdbcType=VARCHAR},
      product_id = #{record.productId,jdbcType=BIGINT},
      product_name = #{record.productName,jdbcType=VARCHAR},
      product_money = #{record.productMoney,jdbcType=DECIMAL},
      product_dou = #{record.productDou,jdbcType=INTEGER},
      product_info_id = #{record.productInfoId,jdbcType=INTEGER},
      amount = #{record.amount,jdbcType=INTEGER},
      total_money = #{record.totalMoney,jdbcType=DECIMAL},
      total_dou = #{record.totalDou,jdbcType=INTEGER},
      pay_way = #{record.payWay,jdbcType=TINYINT},
      charge_no = #{record.chargeNo,jdbcType=VARCHAR},
      coupon_detail = #{record.couponDetail,jdbcType=VARCHAR},
      status = #{record.status,jdbcType=TINYINT},
      coupon_active_id = #{record.couponActiveId,jdbcType=BIGINT},
      addtime = #{record.addtime,jdbcType=TIMESTAMP},
      paytime = #{record.paytime,jdbcType=TIMESTAMP},
      updatetime = #{record.updatetime,jdbcType=TIMESTAMP}
    <if test="_parameter != null">
      <include refid="Update_By_Example_Where_Clause" />
    </if>
  </update>
  <update id="updateByPrimaryKeySelective" parameterType="com.joiest.jpf.common.po.PayShopOrder">
    <!--
      @mbggenerated
      This element is automatically generated by MyBatis Generator,Do not modify ! Generated on Fri Aug 03 13:59:18 CST 2018.
    -->
    update pay_shop_order
    <set>
      <if test="orderNo != null">
        order_no = #{orderNo,jdbcType=VARCHAR},
      </if>
      <if test="customerId != null">
        customer_id = #{customerId,jdbcType=BIGINT},
      </if>
      <if test="customerName != null">
        customer_name = #{customerName,jdbcType=VARCHAR},
      </if>
      <if test="productId != null">
        product_id = #{productId,jdbcType=BIGINT},
      </if>
      <if test="productName != null">
        product_name = #{productName,jdbcType=VARCHAR},
      </if>
      <if test="productMoney != null">
        product_money = #{productMoney,jdbcType=DECIMAL},
      </if>
      <if test="productDou != null">
        product_dou = #{productDou,jdbcType=INTEGER},
      </if>
      <if test="productInfoId != null">
        product_info_id = #{productInfoId,jdbcType=INTEGER},
      </if>
      <if test="amount != null">
        amount = #{amount,jdbcType=INTEGER},
      </if>
      <if test="totalMoney != null">
        total_money = #{totalMoney,jdbcType=DECIMAL},
      </if>
      <if test="totalDou != null">
        total_dou = #{totalDou,jdbcType=INTEGER},
      </if>
      <if test="payWay != null">
        pay_way = #{payWay,jdbcType=TINYINT},
      </if>
      <if test="chargeNo != null">
        charge_no = #{chargeNo,jdbcType=VARCHAR},
      </if>
      <if test="couponDetail != null">
        coupon_detail = #{couponDetail,jdbcType=VARCHAR},
      </if>
      <if test="status != null">
        status = #{status,jdbcType=TINYINT},
      </if>
      <if test="couponActiveId != null">
        coupon_active_id = #{couponActiveId,jdbcType=BIGINT},
      </if>
      <if test="addtime != null">
        addtime = #{addtime,jdbcType=TIMESTAMP},
      </if>
      <if test="paytime != null">
        paytime = #{paytime,jdbcType=TIMESTAMP},
      </if>
      <if test="updatetime != null">
        updatetime = #{updatetime,jdbcType=TIMESTAMP},
      </if>
    </set>
    where id = #{id,jdbcType=BIGINT}
  </update>
  <update id="updateByPrimaryKey" parameterType="com.joiest.jpf.common.po.PayShopOrder">
    <!--
      @mbggenerated
      This element is automatically generated by MyBatis Generator,Do not modify ! Generated on Fri Aug 03 13:59:18 CST 2018.
    -->
    update pay_shop_order
    set order_no = #{orderNo,jdbcType=VARCHAR},
      customer_id = #{customerId,jdbcType=BIGINT},
      customer_name = #{customerName,jdbcType=VARCHAR},
      product_id = #{productId,jdbcType=BIGINT},
      product_name = #{productName,jdbcType=VARCHAR},
      product_money = #{productMoney,jdbcType=DECIMAL},
      product_dou = #{productDou,jdbcType=INTEGER},
      product_info_id = #{productInfoId,jdbcType=INTEGER},
      amount = #{amount,jdbcType=INTEGER},
      total_money = #{totalMoney,jdbcType=DECIMAL},
      total_dou = #{totalDou,jdbcType=INTEGER},
      pay_way = #{payWay,jdbcType=TINYINT},
      charge_no = #{chargeNo,jdbcType=VARCHAR},
      coupon_detail = #{couponDetail,jdbcType=VARCHAR},
      status = #{status,jdbcType=TINYINT},
      coupon_active_id = #{couponActiveId,jdbcType=BIGINT},
      addtime = #{addtime,jdbcType=TIMESTAMP},
      paytime = #{paytime,jdbcType=TIMESTAMP},
      updatetime = #{updatetime,jdbcType=TIMESTAMP}
    where id = #{id,jdbcType=BIGINT}
  </update>

  <!--自定义连表查询数据-->
  <select id="selectByExcelExampleJoin" parameterType="com.joiest.jpf.common.po.PayShopOrderExample" resultMap="BaseResultMap">
    select 
      a.id,
      a.order_no,
      a.product_name,
      b.type_name,
      a.amount,
      a.total_money,
      a.total_dou,
      a.customer_name,
      a.addtime,
      a.paytime,
      a.status,
      a.interface_type,
      a.source
    from 
      pay_shop_order a 
    LEFT JOIN  
      pay_shop_product_info b 
    ON  
      a.product_info_id = b.id
    <if test="_parameter != null">
      <include refid="Example_Where_Clause_Custom" />
    </if>
    <if test="orderByClause != null">
      order by ${orderByClause}
    </if>
  </select>
</mapper>